{"name":"git","slug":"git","count":1,"postlist":[{"title":"git指南","slug":"git指南","date":"2018-12-04T08:05:33.000Z","updated":"2018-12-04T09:20:00.328Z","comments":true,"path":"api/articles/git指南.json","excerpt":"<h1 id=\"git中级指南\"><a href=\"#git中级指南\" class=\"headerlink\" title=\"git中级指南\"></a>git中级指南</h1><h3 id=\"常用命令\"><a href=\"#常用命令\" class=\"headerlink\" title=\"常用命令\"></a>常用命令</h3><p>git status  //查看当前状态</p>\n<p>git log  //查看当前分支commit logs</p>\n<p>git add . //添加当前文件夹下所有变动</p>\n<p>git reset HEAD //重置 HEAD 的状态</p>\n<p>git commit -m “commit message” //commit操作</p>\n<p>git checkout branch_name //检出分支</p>\n<p>git checkout 23abef // 检出指定commit</p>\n<p>git checkout . //还原尚未分级的改动</p>\n<p>git checkout -b branch_name //新建分支<br></p>","keywords":null,"cover":"/2018/12/04/git指南/1.jpg","content":null,"text":"git中级指南常用命令git status  //查看当前状态git log  //查看当前分支commit logsgit add . //添加当前文件夹下所有变动git reset HEAD //重置 HEAD 的状态git commit -m “commit message","link":"","raw":null,"photos":[],"categories":[{"name":"文档","slug":"文档","count":2,"path":"api/categories/文档.json"}],"tags":[{"name":"git","slug":"git","count":1,"path":"api/tags/git.json"}]}]}